jupyterview/__init__.py
jupyterview/_version.py
jupyterview-0.8.0.data/data/share/jupyter/labextensions/jupyterview/package.json
jupyterview-0.8.0.data/data/share/jupyter/labextensions/jupyterview/static/215.b6f63dd895e044ad3ee7.js
jupyterview-0.8.0.data/data/share/jupyter/labextensions/jupyterview/static/333.ff25d901c19462ad2b05.js
jupyterview-0.8.0.data/data/share/jupyter/labextensions/jupyterview/static/487.2228a335fafdfadf8299.js
jupyterview-0.8.0.data/data/share/jupyter/labextensions/jupyterview/static/596.bf3b9bbcd7dbedd4f4d0.js
jupyterview-0.8.0.data/data/share/jupyter/labextensions/jupyterview/static/666.1e2ee671c4958908966e.js
jupyterview-0.8.0.data/data/share/jupyter/labextensions/jupyterview/static/704.ee3057d4d251ee44ee6e.js
jupyterview-0.8.0.data/data/share/jupyter/labextensions/jupyterview/static/714.537231fbc98488babf72.js
jupyterview-0.8.0.data/data/share/jupyter/labextensions/jupyterview/static/728.3a3e61f20f22794322c1.js
jupyterview-0.8.0.data/data/share/jupyter/labextensions/jupyterview/static/834.f6dd05ad2c4ac8a7f4ab.js
jupyterview-0.8.0.data/data/share/jupyter/labextensions/jupyterview/static/868.f5588bb84c065f324a73.js
jupyterview-0.8.0.data/data/share/jupyter/labextensions/jupyterview/static/remoteEntry.f17a441db8b0a6ce6208.js
jupyterview-0.8.0.data/data/share/jupyter/labextensions/jupyterview/static/style.js
jupyterview-0.8.0.data/data/share/jupyter/labextensions/jupyterview/static/third-party-licenses.json
jupyterview-0.8.0.data/data/share/jupyter/labextensions/jupyterview/static/itk/PolyDataIOs/VTKLegacyFileReader.js
jupyterview-0.8.0.data/data/share/jupyter/labextensions/jupyterview/static/itk/PolyDataIOs/VTKLegacyFileReaderWasm.js
jupyterview-0.8.0.data/data/share/jupyter/labextensions/jupyterview/static/itk/PolyDataIOs/VTKLegacyFileReaderWasm.wasm
jupyterview-0.8.0.data/data/share/jupyter/labextensions/jupyterview/static/itk/PolyDataIOs/VTKXMLFileReader.js
jupyterview-0.8.0.dist-info/METADATA
jupyterview-0.8.0.dist-info/WHEEL
jupyterview-0.8.0.dist-info/licenses/LICENSE
jupyterview-0.8.0.dist-info/RECORD
