Metadata-Version: 2.4
Name: jupyterview
Version: 0.8.0
Dynamic: Keywords
Summary: A Jupyterlab VTK viewer extension.
Project-URL: Homepage, https://github.com/trungleduc/jupyterview
Project-URL: Bug Tracker, https://github.com/trungleduc/jupyterview/issues
Project-URL: Repository, https://github.com/trungleduc/jupyterview.git
Author-email: Trung Le <leductrungxf@gmail.com>
License: BSD 3-Clause License
License-File: LICENSE
Classifier: Framework :: Jupyter
Classifier: Framework :: Jupyter :: JupyterLab
Classifier: Framework :: Jupyter :: JupyterLab :: 4
Classifier: Framework :: Jupyter :: JupyterLab :: Extensions
Classifier: Framework :: Jupyter :: JupyterLab :: Extensions :: Prebuilt
Classifier: License :: OSI Approved :: BSD License
Classifier: Programming Language :: Python
Classifier: Programming Language :: Python :: 3
Classifier: Programming Language :: Python :: 3.8
Classifier: Programming Language :: Python :: 3.9
Classifier: Programming Language :: Python :: 3.10
Classifier: Programming Language :: Python :: 3.11
Requires-Python: >=3.8
Requires-Dist: jupyter-server<3,>=1.21
Requires-Dist: meshio
